pdftotree/TreeExtract.py
pdftotree/TreeVisualizer.py
pdftotree/__init__.py
pdftotree/_version.py
pdftotree/core.py
pdftotree/ml/TableExtractML.py
pdftotree/ml/__init__.py
pdftotree/ml/features.py
pdftotree/utils/__init__.py
pdftotree/utils/bbox_utils.py
pdftotree/utils/display_utils.py
pdftotree/utils/img_utils.py
pdftotree/utils/lines_utils.py
pdftotree/utils/pdf/__init__.py
pdftotree/utils/pdf/grid.py
pdftotree/utils/pdf/layout_utils.py
pdftotree/utils/pdf/node.py
pdftotree/utils/pdf/pdf_parsers.py
pdftotree/utils/pdf/pdf_utils.py
pdftotree/utils/pdf/render.py
pdftotree/utils/pdf/vector_utils.py
pdftotree/visual/__init__.py
pdftotree/visual/visual_utils.py
pdftotree_mercurial-1.3.data/scripts/extract_tables
pdftotree_mercurial-1.3.data/scripts/pdftotree
tests/__init__.py
tests/test_basic.py
tests/test_figures.py
tests/test_table_detection.py
tests/test_text.py
pdftotree_mercurial-1.3.dist-info/LICENSE
pdftotree_mercurial-1.3.dist-info/METADATA
pdftotree_mercurial-1.3.dist-info/WHEEL
pdftotree_mercurial-1.3.dist-info/top_level.txt
pdftotree_mercurial-1.3.dist-info/RECORD
